analytics-test/__init__.py
analytics-test/main.py
e2e-server/__init__.py
e2e-server/server.py
rox/__init__.py
rox/core/__init__.py
rox/core/core.py
rox/core/analytics/__init__.py
rox/core/analytics/client.py
rox/core/analytics/client_proxy.py
rox/core/analytics/consumer.py
rox/core/analytics/request.py
rox/core/analytics/utils.py
rox/core/analytics/version.py
rox/core/client/__init__.py
rox/core/client/buid.py
rox/core/client/device_properties.py
rox/core/client/dynamic_api.py
rox/core/client/internal_flags.py
rox/core/client/sdk_settings.py
rox/core/configuration/__init__.py
rox/core/configuration/configuration.py
rox/core/configuration/configuration_fetched_invoker.py
rox/core/configuration/configuration_parser.py
rox/core/configuration/models/__init__.py
rox/core/configuration/models/experiment_model.py
rox/core/configuration/models/target_group_model.py
rox/core/consts/__init__.py
rox/core/consts/build.py
rox/core/consts/environment.py
rox/core/consts/property_type.py
rox/core/context/__init__.py
rox/core/context/merged_context.py
rox/core/custom_properties/__init__.py
rox/core/custom_properties/custom_property.py
rox/core/custom_properties/custom_property_type.py
rox/core/custom_properties/device_property.py
rox/core/entities/__init__.py
rox/core/entities/default_flag_values.py
rox/core/entities/flag.py
rox/core/entities/flag_setter.py
rox/core/entities/rox_base.py
rox/core/entities/rox_double.py
rox/core/entities/rox_int.py
rox/core/entities/rox_string.py
rox/core/error_handling/__init__.py
rox/core/error_handling/exception_trigger.py
rox/core/error_handling/userspace_handler_exception.py
rox/core/error_handling/userspace_unhandled_error_invoker.py
rox/core/impression/__init__.py
rox/core/impression/impression_invoker.py
rox/core/impression/models/__init__.py
rox/core/impression/models/reporting_value.py
rox/core/logging/__init__.py
rox/core/logging/logging.py
rox/core/logging/no_op_logger.py
rox/core/network/__init__.py
rox-6.0.1.dist-info/LICENSE
rox-6.0.1.dist-info/METADATA
rox-6.0.1.dist-info/WHEEL
rox-6.0.1.dist-info/top_level.txt
rox-6.0.1.dist-info/RECORD
