Metadata-Version: 2.1
Name: rox
Version: 6.0.1
Summary: Rollout.io ROX Python SDK
Home-page: https://support.rollout.io/docs/python-api
Author: Rollout.io
Author-email: support@rollout.io
Classifier: Programming Language :: Python :: 3.7
Classifier: Programming Language :: Python :: 3.8
Classifier: Programming Language :: Python :: 3.9
Classifier: Programming Language :: Python :: 3.10
Classifier: Programming Language :: Python :: 3.11
Classifier: Programming Language :: Python :: 3.12
Classifier: License :: Other/Proprietary License
Classifier: Operating System :: OS Independent
Requires-Python: >=3.7, <4
License-File: LICENSE
Requires-Dist: cryptography
Requires-Dist: requests
Requires-Dist: six
Requires-Dist: sseclient-py
Requires-Dist: backoff
Requires-Dist: monotonic
Requires-Dist: python-dateutil
Requires-Dist: packaging
Requires-Dist: futures ; python_version == "3.7"
